pyskidonion/__init__.py
pyskidonion-0.1.0.dist-info/METADATA
pyskidonion-0.1.0.dist-info/WHEEL
pyskidonion-0.1.0.dist-info/RECORD
