Metadata-Version: 2.1
Name: pyskidonion
Version: 0.1.0
Summary: skidonion utils
License: MIT
Author: zszfympx
Author-email: 2792668017@qq.com
Requires-Python: >=3.8,<4.0
Classifier: License :: OSI Approved :: MIT License
Classifier: Programming Language :: Python :: 3
Classifier: Programming Language :: Python :: 3.8
Classifier: Programming Language :: Python :: 3.9
Classifier: Programming Language :: Python :: 3.10
Classifier: Programming Language :: Python :: 3.11
Classifier: Programming Language :: Python :: 3.12
Requires-Dist: requests (>=2.32.3,<3.0.0)
Requires-Dist: setuptools (>=75.1.0,<76.0.0)
